LICENSE
setup.py
test/test_interactive.py
test/test_unittest.py
ygrader/__init__.py
ygrader/deductions.py
ygrader/feedback.py
ygrader/grader.py
ygrader/grades_csv.py
ygrader/grading_item.py
ygrader/grading_item_config.py
ygrader/remote.py
ygrader/score_input.py
ygrader/send_ctrl_backtick.ahk
ygrader/student_repos.py
ygrader/upstream_merger.py
ygrader/utils.py
ygrader.egg-info/PKG-INFO
ygrader.egg-info/SOURCES.txt
ygrader.egg-info/dependency_links.txt
ygrader.egg-info/requires.txt
ygrader.egg-info/top_level.txt