Metadata-Version: 2.4
Name: ygrader
Version: 2.6.6
Summary: Grading scripts used in BYU's Electrical and Computer Engineering Department
Home-page: https://github.com/byu-cpe/ygrader
Author: Jeff Goeders
Author-email: jeff.goeders@gmail.com
License: MIT
License-File: LICENSE
Requires-Dist: pandas>=1.0.0
Requires-Dist: pyyaml
Dynamic: author
Dynamic: author-email
Dynamic: home-page
Dynamic: license
Dynamic: license-file
Dynamic: requires-dist
Dynamic: summary
